pdmreader/__init__.py
pdmreader/command_executor.py
pdmreader/main.py
pdmreader/models.py
pdmreader/parser.py
pdmreader/unicode_formatter.py
pdmreader/typemapping/__init__.py
pdmreader/typemapping/base.py
pdmreader/typemapping/mysql2oracle.py
pdmreader/typemapping/oracle2java.py
pdmreader/typemapping/oracle2mysql.py
pdmreader-0.1.dist-info/METADATA
pdmreader-0.1.dist-info/RECORD
pdmreader-0.1.dist-info/WHEEL
pdmreader-0.1.dist-info/entry_points.txt
pdmreader-0.1.dist-info/top_level.txt
pdmreader-0.1.dist-info/zip-safe
