Metadata-Version: 2.1
Name: pdmreader
Version: 0.1
Summary: Interactive reader for PowerDesigner PDM files
Home-page: https://github.com/bianjp/pdmreader
Author: Bian Jiaping
Author-email: ssbianjp@gmail.com
License: MIT
Keywords: pdm
Platform: UNKNOWN
Classifier: Development Status :: 3 - Alpha
Classifier: Environment :: Console
Classifier: License :: OSI Approved :: MIT License
Classifier: Programming Language :: Python :: 3 :: Only
Classifier: Programming Language :: Python :: 3.7
Requires-Python: >= 3.7
